fastmetrics/__init__.py
fastmetrics/fastmetrics.py
fastmetrics-0.0.10.dist-info/LICENSE
fastmetrics-0.0.10.dist-info/METADATA
fastmetrics-0.0.10.dist-info/WHEEL
fastmetrics-0.0.10.dist-info/top_level.txt
fastmetrics-0.0.10.dist-info/RECORD
