Metadata-Version: 2.1
Name: fastmetrics
Version: 0.0.10
Summary: Does the same thing as sklearn.metrics but 100x faster.
Home-page: https://github.com/SimonFromNeedham/fastmetrics
Author: Simon Albert Traub
Author-email: simontraub@ucla.edu
Project-URL: Bug Tracker, https://github.com/SimonFromNeedham/fastmetrics/issues
Classifier: Programming Language :: Python :: 3
Classifier: License :: OSI Approved :: MIT License
Classifier: Operating System :: OS Independent
Requires-Python: >=3.6
License-File: LICENSE
Requires-Dist: numba (>=0.55.2)
Requires-Dist: numpy (<1.23.0,>=1.22.0)
